world_countries/__init__.py
world_countries/countries.py
world_countries/test.py
world_countries/ar/__init__.py
world_countries/ar/countries.py
world_countries/ch/__init__.py
world_countries/ch/countries.py
world_countries/data/countries_ar.json
world_countries/data/countries_ch.json
world_countries/data/countries_de.json
world_countries/data/countries_en.json
world_countries/data/countries_es.json
world_countries/data/countries_fr.json
world_countries/data/countries_ru.json
world_countries/de/__init__.py
world_countries/de/countries.py
world_countries/es/__init__.py
world_countries/es/countries.py
world_countries/fr/__init__.py
world_countries/fr/countries.py
world_countries/ru/__init__.py
world_countries/ru/countries.py
world_countries/text/extract_country_data.py
world_countries/text/update_json_fields.py
world_countries-1.0.0.dist-info/licenses/LICENSE
world_countries-1.0.0.dist-info/METADATA
world_countries-1.0.0.dist-info/WHEEL
world_countries-1.0.0.dist-info/top_level.txt
world_countries-1.0.0.dist-info/RECORD
