Metadata-Version: 2.4
Name: world-countries
Version: 1.0.0
Summary: A multilingual Python package for retrieving comprehensive data of all countries in the world
Author-email: Andrey Kolomatskiy <kolomatsky.andrew@gmail.com>
Maintainer-email: Andrey Kolomatskiy <kolomatsky.andrew@gmail.com>
License-Expression: MIT
Project-URL: Bug-Reports, https://github.com/g2r4i6e8/world-countries/issues
Project-URL: Source, https://github.com/g2r4i6e8/world-countries
Project-URL: Documentation, https://github.com/g2r4i6e8/world-countries#readme
Keywords: country,world countries,countries info,country information,country data,json,multilingual,internationalization,i18n,localization,translation,capitals,currencies,phone codes,continents,regions,languages,geography,geographic data,country database,world data,arabic,chinese,spanish,french,russian,german,english,country codes,iso codes,emoji flags,country flags
Classifier: Development Status :: 5 - Production/Stable
Classifier: Intended Audience :: Developers
Classifier: Intended Audience :: Science/Research
Classifier: Operating System :: OS Independent
Classifier: Programming Language :: Python :: 3
Classifier: Programming Language :: Python :: 3.7
Classifier: Programming Language :: Python :: 3.8
Classifier: Programming Language :: Python :: 3.9
Classifier: Programming Language :: Python :: 3.10
Classifier: Programming Language :: Python :: 3.11
Classifier: Programming Language :: Python :: 3.12
Classifier: Topic :: Database
Classifier: Topic :: Scientific/Engineering :: Information Analysis
Classifier: Topic :: Software Development :: Libraries :: Python Modules
Classifier: Topic :: Text Processing :: Linguistic
Requires-Python: >=3.7
License-File: LICENSE
Provides-Extra: dev
Requires-Dist: pytest>=6.0; extra == "dev"
Requires-Dist: pytest-cov>=2.0; extra == "dev"
Dynamic: license-file
